datetimetype/__init__.py
datetimetype/datetime_predicates.py
dedupe_variable_datetime-2.0.0.dist-info/METADATA
dedupe_variable_datetime-2.0.0.dist-info/WHEEL
dedupe_variable_datetime-2.0.0.dist-info/top_level.txt
dedupe_variable_datetime-2.0.0.dist-info/RECORD
